tf_annotations/__init__.py
tf_annotations/cmd.py
tf_annotations-0.3.1.dist-info/entry_points.txt
tf_annotations-0.3.1.dist-info/WHEEL
tf_annotations-0.3.1.dist-info/METADATA
tf_annotations-0.3.1.dist-info/RECORD
